{
  "type": "webapp_interactive-scoring_endpoint-range-scoring",
  "hasLegacyBackendURL": false,
  "params": {
    "backendEnabled": true,
    "autoStartBackend": false,
    "envSelection": {
      "envMode": "INHERIT"
    },
    "libraries": [
      "jquery",
      "dataiku"
    ]
  },
  "config": {},
  "name": "prout",
  "apiKey": "DdeEnq7wIXynjMH3EQikW8MFsdzEegkt",
  "versionTag": {
    "versionNumber": 0,
    "lastModifiedBy": {
      "login": "admin"
    },
    "lastModifiedOn": 1554328318812
  },
  "creationTag": {
    "versionNumber": 0,
    "lastModifiedBy": {
      "login": "admin"
    },
    "lastModifiedOn": 1554328318812
  },
  "tags": [],
  "checklists": {
    "checklists": []
  },
  "customFields": {}
}