{
  "type": "STANDARD",
  "hasLegacyBackendURL": false,
  "params": {
    "backendEnabled": true,
    "autoStartBackend": false,
    "envSelection": {
      "envMode": "USE_BUILTIN_MODE"
    },
    "libraries": [
      "jquery",
      "dataiku"
    ]
  },
  "config": {},
  "name": "test",
  "apiKey": "3vKh3qTf38hsSUm4JTFxbv5iW0UPMnhe",
  "versionTag": {
    "versionNumber": 9,
    "lastModifiedBy": {
      "login": "admin"
    },
    "lastModifiedOn": 1553885304034
  },
  "creationTag": {
    "versionNumber": 0,
    "lastModifiedBy": {
      "login": "admin"
    },
    "lastModifiedOn": 1553875101154
  },
  "tags": [],
  "checklists": {
    "checklists": []
  },
  "customFields": {}
}